pysradb/__init__.py
pysradb/__main__.py
pysradb/basedb.py
pysradb/cli.py
pysradb/download.py
pysradb/exceptions.py
pysradb/filter_attrs.py
pysradb/geodb.py
pysradb/geoweb.py
pysradb/search.py
pysradb/sradb.py
pysradb/sraweb.py
pysradb/taxid2name.py
pysradb/utils.py
pysradb-2.5.1.dist-info/METADATA
pysradb-2.5.1.dist-info/WHEEL
pysradb-2.5.1.dist-info/entry_points.txt
pysradb-2.5.1.dist-info/licenses/AUTHORS.md
pysradb-2.5.1.dist-info/licenses/LICENSE
pysradb-2.5.1.dist-info/RECORD
