Metadata-Version: 2.4
Name: pysradb
Version: 2.5.1
Summary: A Python package for interacting with SRAdb and downloading datasets from SRA/ENA/GEO
Project-URL: Homepage, https://saket-choudhary.me/pysradb
Author-email: Saket Choudhary <saketkc@gmail.com>
License: BSD 3-Clause License
License-File: AUTHORS.md
License-File: LICENSE
Keywords: pysradb
Classifier: Development Status :: 5 - Production/Stable
Classifier: Intended Audience :: Healthcare Industry
Classifier: Intended Audience :: Science/Research
Classifier: License :: OSI Approved :: BSD License
Classifier: Natural Language :: English
Classifier: Programming Language :: Python :: 3
Classifier: Programming Language :: Python :: 3.9
Classifier: Programming Language :: Python :: 3.10
Classifier: Programming Language :: Python :: 3.11
Classifier: Programming Language :: Python :: 3.12
Classifier: Programming Language :: Python :: 3.13
Classifier: Topic :: Scientific/Engineering :: Bio-Informatics
Requires-Python: >=3.9
Requires-Dist: lxml>=4.6.3
Requires-Dist: pandas>=1.3.2
Requires-Dist: requests>=2.26.0
Requires-Dist: tqdm>=4.62.1
Requires-Dist: xmltodict>=0.12.0
